vault2env/__init__.py
vault2env/cli.py
vault2env/vault2env.py
vault2env-0.11.0.dist-info/LICENSE
vault2env-0.11.0.dist-info/METADATA
vault2env-0.11.0.dist-info/WHEEL
vault2env-0.11.0.dist-info/entry_points.txt
vault2env-0.11.0.dist-info/top_level.txt
vault2env-0.11.0.dist-info/RECORD
