Metadata-Version: 2.1
Name: vault2env
Version: 0.11.0
Summary: Read from a KV-2 secret path in Vault and create a .env file from the list of key/value pairs.
Home-page: https://github.com/stgraham2000@gmail.com/vault2env
Author: Steve Graham
Author-email: stgraham2000@gmail.com
License: MIT license
Keywords: vault2env
Classifier: Development Status :: 2 - Pre-Alpha
Classifier: Intended Audience :: Developers
Classifier: License :: OSI Approved :: MIT License
Classifier: Natural Language :: English
Classifier: Programming Language :: Python :: 2
Classifier: Programming Language :: Python :: 2.7
Classifier: Programming Language :: Python :: 3
Classifier: Programming Language :: Python :: 3.5
Classifier: Programming Language :: Python :: 3.6
Classifier: Programming Language :: Python :: 3.7
Classifier: Programming Language :: Python :: 3.8
Requires-Python: >=2.7, !=3.0.*, !=3.1.*, !=3.2.*, !=3.3.*, !=3.4.*
License-File: LICENSE
Requires-Dist: hvac >=0.9.5
Requires-Dist: requests >=2.22.0
